odoo/addons/stock_move_original_date/README.rst
odoo/addons/stock_move_original_date/__init__.py
odoo/addons/stock_move_original_date/__manifest__.py
odoo/addons/stock_move_original_date/i18n/it.po
odoo/addons/stock_move_original_date/i18n/stock_move_original_date.pot
odoo/addons/stock_move_original_date/models/__init__.py
odoo/addons/stock_move_original_date/models/stock_move.py
odoo/addons/stock_move_original_date/models/stock_picking.py
odoo/addons/stock_move_original_date/readme/CONTRIBUTORS.md
odoo/addons/stock_move_original_date/readme/DESCRIPTION.md
odoo/addons/stock_move_original_date/readme/USAGE.md
odoo/addons/stock_move_original_date/static/description/icon.png
odoo/addons/stock_move_original_date/static/description/index.html
odoo/addons/stock_move_original_date/tests/__init__.py
odoo/addons/stock_move_original_date/tests/test_stock_move_original_date.py
odoo/addons/stock_move_original_date/views/stock_move_views.xml
odoo/addons/stock_move_original_date/views/stock_picking_views.xml
odoo_addon_stock_move_original_date-18.0.1.0.0.4.dist-info/METADATA
odoo_addon_stock_move_original_date-18.0.1.0.0.4.dist-info/WHEEL
odoo_addon_stock_move_original_date-18.0.1.0.0.4.dist-info/top_level.txt
odoo_addon_stock_move_original_date-18.0.1.0.0.4.dist-info/RECORD
